[{"TIMESTAMP":1710350100000,"AirTF":60.17039,"RH":32.03604,"Rainfall_Tot":0.0},{"TIMESTAMP":1710351000000,"AirTF":59.98357,"RH":34.56199,"Rainfall_Tot":0.0},{"TIMESTAMP":1710351900000,"AirTF":59.3215,"RH":34.95271,"Rainfall_Tot":0.0},{"TIMESTAMP":1710352800000,"AirTF":60.30775,"RH":35.84404,"Rainfall_Tot":0.0},{"TIMESTAMP":1710353700000,"AirTF":58.37369,"RH":38.62182,"Rainfall_Tot":0.0},{"TIMESTAMP":1710354600000,"AirTF":57.9671,"RH":43.46157,"Rainfall_Tot":0.0},{"TIMESTAMP":1710355500000,"AirTF":56.87918,"RH":45.48843,"Rainfall_Tot":0.0},{"TIMESTAMP":1710356400000,"AirTF":56.07698,"RH":46.10656,"Rainfall_Tot":0.0},{"TIMESTAMP":1710357300000,"AirTF":54.27753,"RH":50.73874,"Rainfall_Tot":0.0},{"TIMESTAMP":1710358200000,"AirTF":52.31325,"RH":55.49759,"Rainfall_Tot":0.0},{"TIMESTAMP":1710359100000,"AirTF":0.0,"RH":0.0,"Rainfall_Tot":0.0},{"TIMESTAMP":1710360000000,"AirTF":0.0,"RH":0.0,"Rainfall_Tot":0.0},{"TIMESTAMP":1710360900000,"AirTF":0.0,"RH":0.0,"Rainfall_Tot":0.0},{"TIMESTAMP":1710361800000,"AirTF":0.0,"RH":0.0,"Rainfall_Tot":0.0},{"TIMESTAMP":1710362700000,"AirTF":0.0,"RH":0.0,"Rainfall_Tot":0.0},{"TIMESTAMP":1710363600000,"AirTF":0.0,"RH":0.0,"Rainfall_Tot":0.0},{"TIMESTAMP":1710364500000,"AirTF":0.0,"RH":0.0,"Rainfall_Tot":0.0},{"TIMESTAMP":1710365400000,"AirTF":0.0,"RH":0.0,"Rainfall_Tot":0.0},{"TIMESTAMP":1710366300000,"AirTF":0.0,"RH":0.0,"Rainfall_Tot":0.0},{"TIMESTAMP":1710367200000,"AirTF":0.0,"RH":0.0,"Rainfall_Tot":0.0},{"TIMESTAMP":1710368100000,"AirTF":0.0,"RH":0.0,"Rainfall_Tot":0.0},{"TIMESTAMP":1710369000000,"AirTF":0.0,"RH":0.0,"Rainfall_Tot":0.0},{"TIMESTAMP":1710369900000,"AirTF":0.0,"RH":0.0,"Rainfall_Tot":0.0},{"TIMESTAMP":1710370800000,"AirTF":0.0,"RH":0.0,"Rainfall_Tot":0.0},{"TIMESTAMP":1710371700000,"AirTF":0.0,"RH":0.0,"Rainfall_Tot":0.0},{"TIMESTAMP":1710372600000,"AirTF":0.0,"RH":0.0,"Rainfall_Tot":0.0},{"TIMESTAMP":1710373500000,"AirTF":0.0,"RH":0.0,"Rainfall_Tot":0.0},{"TIMESTAMP":1710374400000,"AirTF":0.0,"RH":0.0,"Rainfall_Tot":0.0},{"TIMESTAMP":1710375300000,"AirTF":0.0,"RH":0.0,"Rainfall_Tot":0.0},{"TIMESTAMP":1710376200000,"AirTF":0.0,"RH":0.0,"Rainfall_Tot":0.0},{"TIMESTAMP":1710377100000,"AirTF":0.0,"RH":0.0,"Rainfall_Tot":0.0},{"TIMESTAMP":1710378000000,"AirTF":0.0,"RH":0.0,"Rainfall_Tot":0.0},{"TIMESTAMP":1710378900000,"AirTF":0.0,"RH":0.0,"Rainfall_Tot":0.0},{"TIMESTAMP":1710379800000,"AirTF":0.0,"RH":0.0,"Rainfall_Tot":0.0},{"TIMESTAMP":1710380700000,"AirTF":0.0,"RH":0.0,"Rainfall_Tot":0.0},{"TIMESTAMP":1710381600000,"AirTF":0.0,"RH":0.0,"Rainfall_Tot":0.0},{"TIMESTAMP":1710382500000,"AirTF":0.0,"RH":0.0,"Rainfall_Tot":0.0},{"TIMESTAMP":1710383400000,"AirTF":0.0,"RH":0.0,"Rainfall_Tot":0.0},{"TIMESTAMP":1710384300000,"AirTF":0.0,"RH":0.0,"Rainfall_Tot":0.0},{"TIMESTAMP":1710385200000,"AirTF":0.0,"RH":0.0,"Rainfall_Tot":0.0},{"TIMESTAMP":1710386100000,"AirTF":0.0,"RH":0.0,"Rainfall_Tot":0.0},{"TIMESTAMP":1710387000000,"AirTF":0.0,"RH":0.0,"Rainfall_Tot":0.0},{"TIMESTAMP":1710387900000,"AirTF":0.0,"RH":0.0,"Rainfall_Tot":0.0},{"TIMESTAMP":1710388800000,"AirTF":0.0,"RH":0.0,"Rainfall_Tot":0.0},{"TIMESTAMP":1710389700000,"AirTF":0.0,"RH":0.0,"Rainfall_Tot":0.0},{"TIMESTAMP":1710390600000,"AirTF":0.0,"RH":0.0,"Rainfall_Tot":0.0},{"TIMESTAMP":1710391500000,"AirTF":0.0,"RH":0.0,"Rainfall_Tot":0.0},{"TIMESTAMP":1710392400000,"AirTF":0.0,"RH":0.0,"Rainfall_Tot":0.0},{"TIMESTAMP":1710393300000,"AirTF":0.0,"RH":0.0,"Rainfall_Tot":0.0},{"TIMESTAMP":1710394200000,"AirTF":0.0,"RH":0.0,"Rainfall_Tot":0.0},{"TIMESTAMP":1710395100000,"AirTF":0.0,"RH":0.0,"Rainfall_Tot":0.0},{"TIMESTAMP":1710396000000,"AirTF":0.0,"RH":0.0,"Rainfall_Tot":0.0},{"TIMESTAMP":1710396900000,"AirTF":0.0,"RH":0.0,"Rainfall_Tot":0.0},{"TIMESTAMP":1710397800000,"AirTF":0.0,"RH":0.0,"Rainfall_Tot":0.0},{"TIMESTAMP":1710398700000,"AirTF":0.0,"RH":0.0,"Rainfall_Tot":0.0},{"TIMESTAMP":1710399600000,"AirTF":0.0,"RH":0.0,"Rainfall_Tot":0.0},{"TIMESTAMP":1710400500000,"AirTF":0.0,"RH":0.0,"Rainfall_Tot":0.0},{"TIMESTAMP":1710401400000,"AirTF":0.0,"RH":0.0,"Rainfall_Tot":0.0},{"TIMESTAMP":1710402300000,"AirTF":0.0,"RH":0.0,"Rainfall_Tot":0.0},{"TIMESTAMP":1710403200000,"AirTF":0.0,"RH":0.0,"Rainfall_Tot":0.0},{"TIMESTAMP":1710404100000,"AirTF":0.0,"RH":0.0,"Rainfall_Tot":0.0},{"TIMESTAMP":1710405000000,"AirTF":0.0,"RH":0.0,"Rainfall_Tot":0.0},{"TIMESTAMP":1710405900000,"AirTF":0.0,"RH":0.0,"Rainfall_Tot":0.0},{"TIMESTAMP":1710406800000,"AirTF":45.26653,"RH":91.9033,"Rainfall_Tot":0.0},{"TIMESTAMP":1710407700000,"AirTF":45.11819,"RH":91.42558,"Rainfall_Tot":0.0},{"TIMESTAMP":1710408600000,"AirTF":45.24181,"RH":89.64291,"Rainfall_Tot":0.0},{"TIMESTAMP":1710409500000,"AirTF":46.14291,"RH":88.58369,"Rainfall_Tot":0.0},{"TIMESTAMP":1710410400000,"AirTF":48.49456,"RH":84.7589,"Rainfall_Tot":0.0},{"TIMESTAMP":1710411300000,"AirTF":47.3627,"RH":82.33675,"Rainfall_Tot":0.0},{"TIMESTAMP":1710412200000,"AirTF":48.52752,"RH":80.57697,"Rainfall_Tot":0.0},{"TIMESTAMP":1710413100000,"AirTF":49.98907,"RH":76.10964,"Rainfall_Tot":0.0},{"TIMESTAMP":1710414000000,"AirTF":56.65666,"RH":68.96677,"Rainfall_Tot":0.0},{"TIMESTAMP":1710414900000,"AirTF":58.29402,"RH":63.44326,"Rainfall_Tot":0.0},{"TIMESTAMP":1710415800000,"AirTF":57.99733,"RH":59.70089,"Rainfall_Tot":0.0},{"TIMESTAMP":1710416700000,"AirTF":60.05226,"RH":56.57513,"Rainfall_Tot":0.0},{"TIMESTAMP":1710417600000,"AirTF":62.15392,"RH":50.13739,"Rainfall_Tot":0.0},{"TIMESTAMP":1710418500000,"AirTF":62.47808,"RH":49.30406,"Rainfall_Tot":0.0},{"TIMESTAMP":1710419400000,"AirTF":63.55501,"RH":48.63404,"Rainfall_Tot":0.0},{"TIMESTAMP":1710420300000,"AirTF":64.8627,"RH":43.09221,"Rainfall_Tot":0.0},{"TIMESTAMP":1710421200000,"AirTF":65.28853,"RH":40.43348,"Rainfall_Tot":0.0},{"TIMESTAMP":1710422100000,"AirTF":66.51105,"RH":39.62915,"Rainfall_Tot":0.0},{"TIMESTAMP":1710423000000,"AirTF":66.92589,"RH":35.99514,"Rainfall_Tot":0.0},{"TIMESTAMP":1710423900000,"AirTF":68.31875,"RH":27.29245,"Rainfall_Tot":0.0},{"TIMESTAMP":1710424800000,"AirTF":69.17865,"RH":26.99483,"Rainfall_Tot":0.0},{"TIMESTAMP":1710425700000,"AirTF":69.01381,"RH":26.82389,"Rainfall_Tot":0.0},{"TIMESTAMP":1710426600000,"AirTF":69.67589,"RH":27.0513,"Rainfall_Tot":0.0},{"TIMESTAMP":1710427500000,"AirTF":71.35996,"RH":28.21278,"Rainfall_Tot":0.0},{"TIMESTAMP":1710428400000,"AirTF":71.5193,"RH":29.12853,"Rainfall_Tot":0.0},{"TIMESTAMP":1710429300000,"AirTF":73.21711,"RH":27.88768,"Rainfall_Tot":0.0},{"TIMESTAMP":1710430200000,"AirTF":73.27753,"RH":27.27261,"Rainfall_Tot":0.0},{"TIMESTAMP":1710431100000,"AirTF":73.13469,"RH":28.53481,"Rainfall_Tot":0.0},{"TIMESTAMP":1710432000000,"AirTF":73.48358,"RH":31.2195,"Rainfall_Tot":0.0},{"TIMESTAMP":1710432900000,"AirTF":73.01381,"RH":30.80893,"Rainfall_Tot":0.0},{"TIMESTAMP":1710433800000,"AirTF":71.63194,"RH":32.59617,"Rainfall_Tot":0.0},{"TIMESTAMP":1710434700000,"AirTF":71.28853,"RH":32.62212,"Rainfall_Tot":0.0},{"TIMESTAMP":1710435600000,"AirTF":71.33797,"RH":31.87426,"Rainfall_Tot":0.0},{"TIMESTAMP":1710436500000,"AirTF":72.16766,"RH":32.85411,"Rainfall_Tot":0.0},{"TIMESTAMP":1710437400000,"AirTF":72.11546,"RH":33.72865,"Rainfall_Tot":0.0},{"TIMESTAMP":1710438300000,"AirTF":70.52753,"RH":35.50216,"Rainfall_Tot":0.0},{"TIMESTAMP":1710439200000,"AirTF":69.89843,"RH":35.88678,"Rainfall_Tot":0.0},{"TIMESTAMP":1710440100000,"AirTF":66.87095,"RH":36.1035,"Rainfall_Tot":0.0},{"TIMESTAMP":1710441000000,"AirTF":65.12369,"RH":40.89288,"Rainfall_Tot":0.0},{"TIMESTAMP":1710441900000,"AirTF":64.1649,"RH":45.96462,"Rainfall_Tot":0.0},{"TIMESTAMP":1710442800000,"AirTF":61.83524,"RH":47.14747,"Rainfall_Tot":0.0},{"TIMESTAMP":1710443700000,"AirTF":60.0715,"RH":48.27384,"Rainfall_Tot":0.0},{"TIMESTAMP":1710444600000,"AirTF":0.0,"RH":0.0,"Rainfall_Tot":0.0},{"TIMESTAMP":1710445500000,"AirTF":0.0,"RH":0.0,"Rainfall_Tot":0.0},{"TIMESTAMP":1710446400000,"AirTF":0.0,"RH":0.0,"Rainfall_Tot":0.0},{"TIMESTAMP":1710447300000,"AirTF":0.0,"RH":0.0,"Rainfall_Tot":0.0},{"TIMESTAMP":1710448200000,"AirTF":0.0,"RH":0.0,"Rainfall_Tot":0.0},{"TIMESTAMP":1710449100000,"AirTF":0.0,"RH":0.0,"Rainfall_Tot":0.0},{"TIMESTAMP":1710450000000,"AirTF":0.0,"RH":0.0,"Rainfall_Tot":0.0},{"TIMESTAMP":1710450900000,"AirTF":0.0,"RH":0.0,"Rainfall_Tot":0.0},{"TIMESTAMP":1710451800000,"AirTF":0.0,"RH":0.0,"Rainfall_Tot":0.0},{"TIMESTAMP":1710452700000,"AirTF":0.0,"RH":0.0,"Rainfall_Tot":0.0},{"TIMESTAMP":1710453600000,"AirTF":0.0,"RH":0.0,"Rainfall_Tot":0.0},{"TIMESTAMP":1710454500000,"AirTF":0.0,"RH":0.0,"Rainfall_Tot":0.0},{"TIMESTAMP":1710455400000,"AirTF":0.0,"RH":0.0,"Rainfall_Tot":0.0},{"TIMESTAMP":1710456300000,"AirTF":0.0,"RH":0.0,"Rainfall_Tot":0.0},{"TIMESTAMP":1710457200000,"AirTF":0.0,"RH":0.0,"Rainfall_Tot":0.0},{"TIMESTAMP":1710458100000,"AirTF":0.0,"RH":0.0,"Rainfall_Tot":0.0},{"TIMESTAMP":1710459000000,"AirTF":0.0,"RH":0.0,"Rainfall_Tot":0.0},{"TIMESTAMP":1710459900000,"AirTF":0.0,"RH":0.0,"Rainfall_Tot":0.0},{"TIMESTAMP":1710460800000,"AirTF":0.0,"RH":0.0,"Rainfall_Tot":0.0},{"TIMESTAMP":1710461700000,"AirTF":0.0,"RH":0.0,"Rainfall_Tot":0.0},{"TIMESTAMP":1710462600000,"AirTF":0.0,"RH":0.0,"Rainfall_Tot":0.0},{"TIMESTAMP":1710463500000,"AirTF":0.0,"RH":0.0,"Rainfall_Tot":0.0},{"TIMESTAMP":1710464400000,"AirTF":0.0,"RH":0.0,"Rainfall_Tot":0.0},{"TIMESTAMP":1710465300000,"AirTF":0.0,"RH":0.0,"Rainfall_Tot":0.0},{"TIMESTAMP":1710466200000,"AirTF":0.0,"RH":0.0,"Rainfall_Tot":0.0},{"TIMESTAMP":1710467100000,"AirTF":0.0,"RH":0.0,"Rainfall_Tot":0.0},{"TIMESTAMP":1710468000000,"AirTF":0.0,"RH":0.0,"Rainfall_Tot":0.0},{"TIMESTAMP":1710468900000,"AirTF":0.0,"RH":0.0,"Rainfall_Tot":0.0},{"TIMESTAMP":1710469800000,"AirTF":0.0,"RH":0.0,"Rainfall_Tot":0.0},{"TIMESTAMP":1710470700000,"AirTF":0.0,"RH":0.0,"Rainfall_Tot":0.0},{"TIMESTAMP":1710471600000,"AirTF":0.0,"RH":0.0,"Rainfall_Tot":0.0},{"TIMESTAMP":1710472500000,"AirTF":0.0,"RH":0.0,"Rainfall_Tot":0.0},{"TIMESTAMP":1710473400000,"AirTF":0.0,"RH":0.0,"Rainfall_Tot":0.0},{"TIMESTAMP":1710474300000,"AirTF":0.0,"RH":0.0,"Rainfall_Tot":0.0},{"TIMESTAMP":1710475200000,"AirTF":0.0,"RH":0.0,"Rainfall_Tot":0.0},{"TIMESTAMP":1710476100000,"AirTF":0.0,"RH":0.0,"Rainfall_Tot":0.0},{"TIMESTAMP":1710477000000,"AirTF":0.0,"RH":0.0,"Rainfall_Tot":0.0},{"TIMESTAMP":1710477900000,"AirTF":0.0,"RH":0.0,"Rainfall_Tot":0.0},{"TIMESTAMP":1710478800000,"AirTF":0.0,"RH":0.0,"Rainfall_Tot":0.0},{"TIMESTAMP":1710479700000,"AirTF":0.0,"RH":0.0,"Rainfall_Tot":0.0},{"TIMESTAMP":1710480600000,"AirTF":0.0,"RH":0.0,"Rainfall_Tot":0.0},{"TIMESTAMP":1710481500000,"AirTF":0.0,"RH":0.0,"Rainfall_Tot":0.0},{"TIMESTAMP":1710482400000,"AirTF":0.0,"RH":0.0,"Rainfall_Tot":0.0},{"TIMESTAMP":1710483300000,"AirTF":0.0,"RH":0.0,"Rainfall_Tot":0.0},{"TIMESTAMP":1710484200000,"AirTF":0.0,"RH":0.0,"Rainfall_Tot":0.0},{"TIMESTAMP":1710485100000,"AirTF":0.0,"RH":0.0,"Rainfall_Tot":0.0},{"TIMESTAMP":1710486000000,"AirTF":0.0,"RH":0.0,"Rainfall_Tot":0.0},{"TIMESTAMP":1710486900000,"AirTF":0.0,"RH":0.0,"Rainfall_Tot":0.0},{"TIMESTAMP":1710487800000,"AirTF":0.0,"RH":0.0,"Rainfall_Tot":0.0},{"TIMESTAMP":1710488700000,"AirTF":0.0,"RH":0.0,"Rainfall_Tot":0.0},{"TIMESTAMP":1710489600000,"AirTF":0.0,"RH":0.0,"Rainfall_Tot":0.0},{"TIMESTAMP":1710490500000,"AirTF":0.0,"RH":0.0,"Rainfall_Tot":0.0},{"TIMESTAMP":1710491400000,"AirTF":0.0,"RH":0.0,"Rainfall_Tot":0.0},{"TIMESTAMP":1710492300000,"AirTF":0.0,"RH":0.0,"Rainfall_Tot":0.0},{"TIMESTAMP":1710493200000,"AirTF":0.0,"RH":0.0,"Rainfall_Tot":0.0},{"TIMESTAMP":1710494100000,"AirTF":0.0,"RH":0.0,"Rainfall_Tot":0.0},{"TIMESTAMP":1710495000000,"AirTF":60.43414,"RH":56.46066,"Rainfall_Tot":0.0},{"TIMESTAMP":1710495900000,"AirTF":62.5193,"RH":56.02415,"Rainfall_Tot":0.0},{"TIMESTAMP":1710496800000,"AirTF":63.20337,"RH":57.00553,"Rainfall_Tot":0.0},{"TIMESTAMP":1710497700000,"AirTF":63.25006,"RH":57.84802,"Rainfall_Tot":0.0},{"TIMESTAMP":1710498600000,"AirTF":63.29402,"RH":59.59863,"Rainfall_Tot":0.0},{"TIMESTAMP":1710499500000,"AirTF":64.00281,"RH":59.98782,"Rainfall_Tot":0.0},{"TIMESTAMP":1710500400000,"AirTF":65.22809,"RH":60.72501,"Rainfall_Tot":0.0},{"TIMESTAMP":1710501300000,"AirTF":66.70612,"RH":62.35963,"Rainfall_Tot":0.0},{"TIMESTAMP":1710502200000,"AirTF":66.28578,"RH":62.09711,"Rainfall_Tot":0.0},{"TIMESTAMP":1710503100000,"AirTF":70.48359,"RH":63.07849,"Rainfall_Tot":0.0},{"TIMESTAMP":1710504000000,"AirTF":70.20887,"RH":61.29735,"Rainfall_Tot":0.0},{"TIMESTAMP":1710504900000,"AirTF":69.61819,"RH":59.95272,"Rainfall_Tot":0.0},{"TIMESTAMP":1710505800000,"AirTF":70.12094,"RH":57.62977,"Rainfall_Tot":0.0},{"TIMESTAMP":1710506700000,"AirTF":75.14018,"RH":57.6725,"Rainfall_Tot":0.0},{"TIMESTAMP":1710507600000,"AirTF":76.5605,"RH":55.79216,"Rainfall_Tot":0.0},{"TIMESTAMP":1710508500000,"AirTF":79.49734,"RH":56.67891,"Rainfall_Tot":0.0},{"TIMESTAMP":1710509400000,"AirTF":70.9149,"RH":51.85138,"Rainfall_Tot":0.0},{"TIMESTAMP":1710510300000,"AirTF":69.84348,"RH":50.33123,"Rainfall_Tot":0.0},{"TIMESTAMP":1710511200000,"AirTF":73.44788,"RH":61.69723,"Rainfall_Tot":0.0},{"TIMESTAMP":1710512100000,"AirTF":76.37095,"RH":61.04094,"Rainfall_Tot":0.0},{"TIMESTAMP":1710513000000,"AirTF":75.3215,"RH":55.67311,"Rainfall_Tot":0.0},{"TIMESTAMP":1710513900000,"AirTF":73.0193,"RH":54.90388,"Rainfall_Tot":0.0},{"TIMESTAMP":1710514800000,"AirTF":71.13469,"RH":52.03148,"Rainfall_Tot":0.0},{"TIMESTAMP":1710515700000,"AirTF":76.55228,"RH":51.67128,"Rainfall_Tot":0.0},{"TIMESTAMP":1710516600000,"AirTF":77.64018,"RH":47.01163,"Rainfall_Tot":0.0},{"TIMESTAMP":1710517500000,"AirTF":75.58798,"RH":47.41151,"Rainfall_Tot":0.0},{"TIMESTAMP":1710518400000,"AirTF":75.50008,"RH":48.23111,"Rainfall_Tot":0.0},{"TIMESTAMP":1710519300000,"AirTF":73.49731,"RH":46.24698,"Rainfall_Tot":0.0},{"TIMESTAMP":1710520200000,"AirTF":75.18964,"RH":42.29246,"Rainfall_Tot":0.0},{"TIMESTAMP":1710521100000,"AirTF":74.81326,"RH":40.71126,"Rainfall_Tot":0.0},{"TIMESTAMP":1710522000000,"AirTF":72.09348,"RH":40.43501,"Rainfall_Tot":0.0},{"TIMESTAMP":1710522900000,"AirTF":70.53854,"RH":40.85015,"Rainfall_Tot":0.0},{"TIMESTAMP":1710523800000,"AirTF":72.52204,"RH":41.40418,"Rainfall_Tot":0.0},{"TIMESTAMP":1710524700000,"AirTF":71.43964,"RH":41.22103,"Rainfall_Tot":0.0},{"TIMESTAMP":1710525600000,"AirTF":71.51656,"RH":41.46523,"Rainfall_Tot":0.0},{"TIMESTAMP":1710526500000,"AirTF":70.98359,"RH":42.33519,"Rainfall_Tot":0.0},{"TIMESTAMP":1710527400000,"AirTF":69.04402,"RH":40.83183,"Rainfall_Tot":0.0},{"TIMESTAMP":1710528300000,"AirTF":65.53853,"RH":40.81352,"Rainfall_Tot":0.0},{"TIMESTAMP":1710529200000,"AirTF":62.43962,"RH":46.64991,"Rainfall_Tot":0.0},{"TIMESTAMP":1710530100000,"AirTF":60.98358,"RH":51.06688,"Rainfall_Tot":0.0},{"TIMESTAMP":1710531000000,"AirTF":59.82699,"RH":53.44783,"Rainfall_Tot":0.0},{"TIMESTAMP":1710531900000,"AirTF":59.07423,"RH":51.44081,"Rainfall_Tot":0.0},{"TIMESTAMP":1710532800000,"AirTF":59.08798,"RH":51.13251,"Rainfall_Tot":0.0},{"TIMESTAMP":1710533700000,"AirTF":57.03027,"RH":55.12214,"Rainfall_Tot":0.0},{"TIMESTAMP":1710534600000,"AirTF":56.84072,"RH":54.94204,"Rainfall_Tot":0.0},{"TIMESTAMP":1710535500000,"AirTF":56.18962,"RH":57.01316,"Rainfall_Tot":0.0},{"TIMESTAMP":1710536400000,"AirTF":54.72809,"RH":60.1313,"Rainfall_Tot":0.0},{"TIMESTAMP":1710537300000,"AirTF":54.96709,"RH":60.0504,"Rainfall_Tot":0.0},{"TIMESTAMP":1710538200000,"AirTF":54.32423,"RH":60.38008,"Rainfall_Tot":0.0},{"TIMESTAMP":1710539100000,"AirTF":53.37917,"RH":62.11848,"Rainfall_Tot":0.0},{"TIMESTAMP":1710540000000,"AirTF":53.2061,"RH":62.43593,"Rainfall_Tot":0.0},{"TIMESTAMP":1710540900000,"AirTF":53.02203,"RH":63.12123,"Rainfall_Tot":0.0},{"TIMESTAMP":1710541800000,"AirTF":53.14017,"RH":62.265,"Rainfall_Tot":0.0},{"TIMESTAMP":1710542700000,"AirTF":0.0,"RH":0.0,"Rainfall_Tot":0.0},{"TIMESTAMP":1710543600000,"AirTF":0.0,"RH":0.0,"Rainfall_Tot":0.0},{"TIMESTAMP":1710544500000,"AirTF":0.0,"RH":0.0,"Rainfall_Tot":0.0},{"TIMESTAMP":1710545400000,"AirTF":0.0,"RH":0.0,"Rainfall_Tot":0.0},{"TIMESTAMP":1710546300000,"AirTF":0.0,"RH":0.0,"Rainfall_Tot":0.0},{"TIMESTAMP":1710547200000,"AirTF":0.0,"RH":0.0,"Rainfall_Tot":0.0},{"TIMESTAMP":1710548100000,"AirTF":0.0,"RH":0.0,"Rainfall_Tot":0.0},{"TIMESTAMP":1710549000000,"AirTF":0.0,"RH":0.0,"Rainfall_Tot":0.0},{"TIMESTAMP":1710549900000,"AirTF":0.0,"RH":0.0,"Rainfall_Tot":0.0},{"TIMESTAMP":1710550800000,"AirTF":0.0,"RH":0.0,"Rainfall_Tot":0.0},{"TIMESTAMP":1710551700000,"AirTF":0.0,"RH":0.0,"Rainfall_Tot":0.0},{"TIMESTAMP":1710552600000,"AirTF":0.0,"RH":0.0,"Rainfall_Tot":0.0},{"TIMESTAMP":1710553500000,"AirTF":0.0,"RH":0.0,"Rainfall_Tot":0.0},{"TIMESTAMP":1710554400000,"AirTF":0.0,"RH":0.0,"Rainfall_Tot":0.0},{"TIMESTAMP":1710555300000,"AirTF":0.0,"RH":0.0,"Rainfall_Tot":0.0},{"TIMESTAMP":1710556200000,"AirTF":0.0,"RH":0.0,"Rainfall_Tot":0.0},{"TIMESTAMP":1710557100000,"AirTF":0.0,"RH":0.0,"Rainfall_Tot":0.0},{"TIMESTAMP":1710558000000,"AirTF":0.0,"RH":0.0,"Rainfall_Tot":0.0},{"TIMESTAMP":1710558900000,"AirTF":0.0,"RH":0.0,"Rainfall_Tot":0.0},{"TIMESTAMP":1710559800000,"AirTF":0.0,"RH":0.0,"Rainfall_Tot":0.0},{"TIMESTAMP":1710560700000,"AirTF":0.0,"RH":0.0,"Rainfall_Tot":0.0},{"TIMESTAMP":1710561600000,"AirTF":0.0,"RH":0.0,"Rainfall_Tot":0.0},{"TIMESTAMP":1710562500000,"AirTF":0.0,"RH":0.0,"Rainfall_Tot":0.0},{"TIMESTAMP":1710563400000,"AirTF":0.0,"RH":0.0,"Rainfall_Tot":0.0},{"TIMESTAMP":1710564300000,"AirTF":0.0,"RH":0.0,"Rainfall_Tot":0.0},{"TIMESTAMP":1710565200000,"AirTF":0.0,"RH":0.0,"Rainfall_Tot":0.0},{"TIMESTAMP":1710566100000,"AirTF":0.0,"RH":0.0,"Rainfall_Tot":0.0},{"TIMESTAMP":1710567000000,"AirTF":0.0,"RH":0.0,"Rainfall_Tot":0.0},{"TIMESTAMP":1710567900000,"AirTF":0.0,"RH":0.0,"Rainfall_Tot":0.0},{"TIMESTAMP":1710568800000,"AirTF":0.0,"RH":0.0,"Rainfall_Tot":0.0},{"TIMESTAMP":1710569700000,"AirTF":0.0,"RH":0.0,"Rainfall_Tot":0.0},{"TIMESTAMP":1710570600000,"AirTF":0.0,"RH":0.0,"Rainfall_Tot":0.0},{"TIMESTAMP":1710571500000,"AirTF":0.0,"RH":0.0,"Rainfall_Tot":0.0},{"TIMESTAMP":1710572400000,"AirTF":0.0,"RH":0.0,"Rainfall_Tot":0.0},{"TIMESTAMP":1710573300000,"AirTF":0.0,"RH":0.0,"Rainfall_Tot":0.0},{"TIMESTAMP":1710574200000,"AirTF":0.0,"RH":0.0,"Rainfall_Tot":0.0},{"TIMESTAMP":1710575100000,"AirTF":0.0,"RH":0.0,"Rainfall_Tot":0.0},{"TIMESTAMP":1710576000000,"AirTF":0.0,"RH":0.0,"Rainfall_Tot":0.0},{"TIMESTAMP":1710576900000,"AirTF":0.0,"RH":0.0,"Rainfall_Tot":0.0},{"TIMESTAMP":1710577800000,"AirTF":0.0,"RH":0.0,"Rainfall_Tot":0.0},{"TIMESTAMP":1710578700000,"AirTF":46.76104,"RH":84.84743,"Rainfall_Tot":0.0},{"TIMESTAMP":1710579600000,"AirTF":46.95885,"RH":78.72258,"Rainfall_Tot":0.0},{"TIMESTAMP":1710580500000,"AirTF":47.37094,"RH":73.42801,"Rainfall_Tot":0.0},{"TIMESTAMP":1710581400000,"AirTF":47.83797,"RH":67.53057,"Rainfall_Tot":0.0},{"TIMESTAMP":1710582300000,"AirTF":48.79401,"RH":64.54217,"Rainfall_Tot":0.0},{"TIMESTAMP":1710583200000,"AirTF":49.64566,"RH":63.23111,"Rainfall_Tot":0.0},{"TIMESTAMP":1710584100000,"AirTF":50.29951,"RH":59.74973,"Rainfall_Tot":0.0},{"TIMESTAMP":1710585000000,"AirTF":50.81874,"RH":59.50858,"Rainfall_Tot":0.0},{"TIMESTAMP":1710585900000,"AirTF":52.77478,"RH":56.46524,"Rainfall_Tot":0.0},{"TIMESTAMP":1710586800000,"AirTF":53.73632,"RH":55.22745,"Rainfall_Tot":0.0},{"TIMESTAMP":1710587700000,"AirTF":54.03577,"RH":53.93471,"Rainfall_Tot":0.0},{"TIMESTAMP":1710588600000,"AirTF":54.56874,"RH":52.53666,"Rainfall_Tot":0.0},{"TIMESTAMP":1710589500000,"AirTF":56.12643,"RH":51.10962,"Rainfall_Tot":0.0},{"TIMESTAMP":1710590400000,"AirTF":55.20885,"RH":49.56658,"Rainfall_Tot":0.0},{"TIMESTAMP":1710591300000,"AirTF":56.69786,"RH":52.97165,"Rainfall_Tot":0.0},{"TIMESTAMP":1710592200000,"AirTF":58.1127,"RH":51.12336,"Rainfall_Tot":0.0},{"TIMESTAMP":1710593100000,"AirTF":56.45336,"RH":45.72042,"Rainfall_Tot":0.0},{"TIMESTAMP":1710594000000,"AirTF":56.10171,"RH":47.32756,"Rainfall_Tot":0.0},{"TIMESTAMP":1710594900000,"AirTF":58.21435,"RH":46.65601,"Rainfall_Tot":0.0},{"TIMESTAMP":1710595800000,"AirTF":60.37643,"RH":47.79918,"Rainfall_Tot":0.0},{"TIMESTAMP":1710596700000,"AirTF":62.64017,"RH":49.08581,"Rainfall_Tot":0.0},{"TIMESTAMP":1710597600000,"AirTF":59.69237,"RH":47.10778,"Rainfall_Tot":0.0},{"TIMESTAMP":1710598500000,"AirTF":57.67314,"RH":43.8645,"Rainfall_Tot":0.0},{"TIMESTAMP":1710599400000,"AirTF":58.49732,"RH":44.60778,"Rainfall_Tot":0.0},{"TIMESTAMP":1710600300000,"AirTF":57.79677,"RH":42.22836,"Rainfall_Tot":0.0},{"TIMESTAMP":1710601200000,"AirTF":62.25556,"RH":44.63372,"Rainfall_Tot":0.0},{"TIMESTAMP":1710602100000,"AirTF":58.58798,"RH":44.51773,"Rainfall_Tot":0.0},{"TIMESTAMP":1710603000000,"AirTF":64.35172,"RH":48.71035,"Rainfall_Tot":0.0},{"TIMESTAMP":1710603900000,"AirTF":59.51929,"RH":48.49209,"Rainfall_Tot":0.0},{"TIMESTAMP":1710604800000,"AirTF":58.12094,"RH":48.40357,"Rainfall_Tot":0.0},{"TIMESTAMP":1710605700000,"AirTF":58.4726,"RH":49.58184,"Rainfall_Tot":0.0},{"TIMESTAMP":1710606600000,"AirTF":57.2116,"RH":49.65052,"Rainfall_Tot":0.0},{"TIMESTAMP":1710607500000,"AirTF":56.48633,"RH":51.57817,"Rainfall_Tot":0.0},{"TIMESTAMP":1710608400000,"AirTF":56.03028,"RH":52.08947,"Rainfall_Tot":0.0},{"TIMESTAMP":1710609300000,"AirTF":56.28303,"RH":55.82116,"Rainfall_Tot":0.0},{"TIMESTAMP":1710610200000,"AirTF":55.38467,"RH":59.45059,"Rainfall_Tot":0.0},{"TIMESTAMP":1710611100000,"AirTF":54.93412,"RH":61.08826,"Rainfall_Tot":0.0},{"TIMESTAMP":1710612000000,"AirTF":54.54401,"RH":61.63771,"Rainfall_Tot":0.0},{"TIMESTAMP":1710612900000,"AirTF":54.09896,"RH":61.6316,"Rainfall_Tot":0.0},{"TIMESTAMP":1710613800000,"AirTF":53.91214,"RH":62.236,"Rainfall_Tot":0.0},{"TIMESTAMP":1710614700000,"AirTF":53.09347,"RH":64.10871,"Rainfall_Tot":0.0},{"TIMESTAMP":1710615600000,"AirTF":52.3627,"RH":64.4918,"Rainfall_Tot":0.0},{"TIMESTAMP":1710616500000,"AirTF":52.22258,"RH":64.5269,"Rainfall_Tot":0.0},{"TIMESTAMP":1710617400000,"AirTF":0.0,"RH":0.0,"Rainfall_Tot":0.0},{"TIMESTAMP":1710618300000,"AirTF":0.0,"RH":0.0,"Rainfall_Tot":0.0},{"TIMESTAMP":1710619200000,"AirTF":0.0,"RH":0.0,"Rainfall_Tot":0.0},{"TIMESTAMP":1710620100000,"AirTF":0.0,"RH":0.0,"Rainfall_Tot":0.0},{"TIMESTAMP":1710621000000,"AirTF":0.0,"RH":0.0,"Rainfall_Tot":0.0},{"TIMESTAMP":1710621900000,"AirTF":0.0,"RH":0.0,"Rainfall_Tot":0.0},{"TIMESTAMP":1710622800000,"AirTF":0.0,"RH":0.0,"Rainfall_Tot":0.0},{"TIMESTAMP":1710623700000,"AirTF":0.0,"RH":0.0,"Rainfall_Tot":0.0},{"TIMESTAMP":1710624600000,"AirTF":0.0,"RH":0.0,"Rainfall_Tot":0.0},{"TIMESTAMP":1710625500000,"AirTF":0.0,"RH":0.0,"Rainfall_Tot":0.0},{"TIMESTAMP":1710626400000,"AirTF":0.0,"RH":0.0,"Rainfall_Tot":0.0},{"TIMESTAMP":1710627300000,"AirTF":0.0,"RH":0.0,"Rainfall_Tot":0.0},{"TIMESTAMP":1710628200000,"AirTF":0.0,"RH":0.0,"Rainfall_Tot":0.0},{"TIMESTAMP":1710629100000,"AirTF":0.0,"RH":0.0,"Rainfall_Tot":0.0},{"TIMESTAMP":1710630000000,"AirTF":0.0,"RH":0.0,"Rainfall_Tot":0.0},{"TIMESTAMP":1710630900000,"AirTF":0.0,"RH":0.0,"Rainfall_Tot":0.0},{"TIMESTAMP":1710631800000,"AirTF":0.0,"RH":0.0,"Rainfall_Tot":0.0},{"TIMESTAMP":1710632700000,"AirTF":0.0,"RH":0.0,"Rainfall_Tot":0.0},{"TIMESTAMP":1710633600000,"AirTF":0.0,"RH":0.0,"Rainfall_Tot":0.0},{"TIMESTAMP":1710634500000,"AirTF":0.0,"RH":0.0,"Rainfall_Tot":0.0},{"TIMESTAMP":1710635400000,"AirTF":0.0,"RH":0.0,"Rainfall_Tot":0.0},{"TIMESTAMP":1710636300000,"AirTF":0.0,"RH":0.0,"Rainfall_Tot":0.0},{"TIMESTAMP":1710637200000,"AirTF":0.0,"RH":0.0,"Rainfall_Tot":0.0},{"TIMESTAMP":1710638100000,"AirTF":0.0,"RH":0.0,"Rainfall_Tot":0.0},{"TIMESTAMP":1710639000000,"AirTF":0.0,"RH":0.0,"Rainfall_Tot":0.0},{"TIMESTAMP":1710639900000,"AirTF":0.0,"RH":0.0,"Rainfall_Tot":0.0},{"TIMESTAMP":1710640800000,"AirTF":0.0,"RH":0.0,"Rainfall_Tot":0.0},{"TIMESTAMP":1710641700000,"AirTF":0.0,"RH":0.0,"Rainfall_Tot":0.0},{"TIMESTAMP":1710642600000,"AirTF":0.0,"RH":0.0,"Rainfall_Tot":0.0},{"TIMESTAMP":1710643500000,"AirTF":0.0,"RH":0.0,"Rainfall_Tot":0.0},{"TIMESTAMP":1710644400000,"AirTF":0.0,"RH":0.0,"Rainfall_Tot":0.0},{"TIMESTAMP":1710645300000,"AirTF":0.0,"RH":0.0,"Rainfall_Tot":0.0},{"TIMESTAMP":1710646200000,"AirTF":0.0,"RH":0.0,"Rainfall_Tot":0.0},{"TIMESTAMP":1710647100000,"AirTF":0.0,"RH":0.0,"Rainfall_Tot":0.0},{"TIMESTAMP":1710648000000,"AirTF":0.0,"RH":0.0,"Rainfall_Tot":0.0},{"TIMESTAMP":1710648900000,"AirTF":0.0,"RH":0.0,"Rainfall_Tot":0.0},{"TIMESTAMP":1710649800000,"AirTF":0.0,"RH":0.0,"Rainfall_Tot":0.0},{"TIMESTAMP":1710650700000,"AirTF":0.0,"RH":0.0,"Rainfall_Tot":0.0},{"TIMESTAMP":1710651600000,"AirTF":0.0,"RH":0.0,"Rainfall_Tot":0.0},{"TIMESTAMP":1710652500000,"AirTF":0.0,"RH":0.0,"Rainfall_Tot":0.0},{"TIMESTAMP":1710653400000,"AirTF":0.0,"RH":0.0,"Rainfall_Tot":0.0},{"TIMESTAMP":1710654300000,"AirTF":0.0,"RH":0.0,"Rainfall_Tot":0.0},{"TIMESTAMP":1710655200000,"AirTF":0.0,"RH":0.0,"Rainfall_Tot":0.0},{"TIMESTAMP":1710656100000,"AirTF":0.0,"RH":0.0,"Rainfall_Tot":0.0},{"TIMESTAMP":1710657000000,"AirTF":0.0,"RH":0.0,"Rainfall_Tot":0.0},{"TIMESTAMP":1710657900000,"AirTF":0.0,"RH":0.0,"Rainfall_Tot":0.0},{"TIMESTAMP":1710658800000,"AirTF":0.0,"RH":0.0,"Rainfall_Tot":0.0},{"TIMESTAMP":1710659700000,"AirTF":0.0,"RH":0.0,"Rainfall_Tot":0.0},{"TIMESTAMP":1710660600000,"AirTF":0.0,"RH":0.0,"Rainfall_Tot":0.0},{"TIMESTAMP":1710661500000,"AirTF":0.0,"RH":0.0,"Rainfall_Tot":0.0},{"TIMESTAMP":1710662400000,"AirTF":0.0,"RH":0.0,"Rainfall_Tot":0.0},{"TIMESTAMP":1710663300000,"AirTF":0.0,"RH":0.0,"Rainfall_Tot":0.0},{"TIMESTAMP":1710664200000,"AirTF":0.0,"RH":0.0,"Rainfall_Tot":0.0},{"TIMESTAMP":1710665100000,"AirTF":52.16214,"RH":75.6365,"Rainfall_Tot":0.0},{"TIMESTAMP":1710666000000,"AirTF":52.54401,"RH":73.72563,"Rainfall_Tot":0.0},{"TIMESTAMP":1710666900000,"AirTF":53.88467,"RH":70.20151,"Rainfall_Tot":0.0},{"TIMESTAMP":1710667800000,"AirTF":55.07973,"RH":67.4161,"Rainfall_Tot":0.0},{"TIMESTAMP":1710668700000,"AirTF":57.10171,"RH":63.10902,"Rainfall_Tot":0.0},{"TIMESTAMP":1710669600000,"AirTF":54.72809,"RH":59.14991,"Rainfall_Tot":0.0},{"TIMESTAMP":1710670500000,"AirTF":53.53578,"RH":58.41578,"Rainfall_Tot":0.0},{"TIMESTAMP":1710671400000,"AirTF":54.67314,"RH":60.80132,"Rainfall_Tot":0.0},{"TIMESTAMP":1710672300000,"AirTF":57.15117,"RH":57.08032,"Rainfall_Tot":0.0},{"TIMESTAMP":1710673200000,"AirTF":58.24457,"RH":55.36634,"Rainfall_Tot":0.0},{"TIMESTAMP":1710674100000,"AirTF":60.73907,"RH":52.27873,"Rainfall_Tot":0.0},{"TIMESTAMP":1710675000000,"AirTF":60.09072,"RH":48.93318,"Rainfall_Tot":0.0},{"TIMESTAMP":1710675900000,"AirTF":61.36271,"RH":47.50308,"Rainfall_Tot":0.0},{"TIMESTAMP":1710676800000,"AirTF":59.38742,"RH":39.89319,"Rainfall_Tot":0.0},{"TIMESTAMP":1710677700000,"AirTF":58.77205,"RH":39.446,"Rainfall_Tot":0.0},{"TIMESTAMP":1710678600000,"AirTF":60.42039,"RH":39.4231,"Rainfall_Tot":0.0},{"TIMESTAMP":1710679500000,"AirTF":61.28852,"RH":39.32084,"Rainfall_Tot":0.0},{"TIMESTAMP":1710680400000,"AirTF":61.93413,"RH":39.11785,"Rainfall_Tot":0.0},{"TIMESTAMP":1710681300000,"AirTF":62.33797,"RH":34.55436,"Rainfall_Tot":0.0},{"TIMESTAMP":1710682200000,"AirTF":60.90391,"RH":32.87701,"Rainfall_Tot":0.0},{"TIMESTAMP":1710683100000,"AirTF":62.2116,"RH":35.82267,"Rainfall_Tot":0.0},{"TIMESTAMP":1710684000000,"AirTF":61.48358,"RH":36.74606,"Rainfall_Tot":0.0},{"TIMESTAMP":1710684900000,"AirTF":62.79402,"RH":31.83916,"Rainfall_Tot":0.0},{"TIMESTAMP":1710685800000,"AirTF":63.26654,"RH":31.63158,"Rainfall_Tot":0.0},{"TIMESTAMP":1710686700000,"AirTF":64.46159,"RH":29.31015,"Rainfall_Tot":0.0},{"TIMESTAMP":1710687600000,"AirTF":63.19238,"RH":28.31809,"Rainfall_Tot":0.0},{"TIMESTAMP":1710688500000,"AirTF":66.15117,"RH":27.89226,"Rainfall_Tot":0.0},{"TIMESTAMP":1710689400000,"AirTF":66.68413,"RH":29.42767,"Rainfall_Tot":0.0},{"TIMESTAMP":1710690300000,"AirTF":65.9149,"RH":26.01955,"Rainfall_Tot":0.0},{"TIMESTAMP":1710691200000,"AirTF":66.61819,"RH":28.73018,"Rainfall_Tot":0.0},{"TIMESTAMP":1710692100000,"AirTF":65.5605,"RH":26.54458,"Rainfall_Tot":0.0},{"TIMESTAMP":1710693000000,"AirTF":63.17864,"RH":26.56595,"Rainfall_Tot":0.0},{"TIMESTAMP":1710693900000,"AirTF":63.62919,"RH":25.10075,"Rainfall_Tot":0.0},{"TIMESTAMP":1710694800000,"AirTF":61.68414,"RH":23.08457,"Rainfall_Tot":0.0},{"TIMESTAMP":1710695700000,"AirTF":62.84622,"RH":23.12425,"Rainfall_Tot":0.0},{"TIMESTAMP":1710696600000,"AirTF":62.59622,"RH":24.34831,"Rainfall_Tot":0.0},{"TIMESTAMP":1710697500000,"AirTF":61.95886,"RH":24.13463,"Rainfall_Tot":0.0},{"TIMESTAMP":1710698400000,"AirTF":61.68138,"RH":22.86479,"Rainfall_Tot":0.0},{"TIMESTAMP":1710699300000,"AirTF":61.25556,"RH":22.53512,"Rainfall_Tot":0.0},{"TIMESTAMP":1710700200000,"AirTF":60.74182,"RH":22.65417,"Rainfall_Tot":0.0},{"TIMESTAMP":1710701100000,"AirTF":60.60171,"RH":22.25276,"Rainfall_Tot":0.0},{"TIMESTAMP":1710702000000,"AirTF":60.1182,"RH":22.96247,"Rainfall_Tot":0.0},{"TIMESTAMP":1710702900000,"AirTF":59.60172,"RH":23.6737,"Rainfall_Tot":0.0},{"TIMESTAMP":1710703800000,"AirTF":58.89566,"RH":24.87944,"Rainfall_Tot":0.0},{"TIMESTAMP":1710704700000,"AirTF":57.76929,"RH":26.81626,"Rainfall_Tot":0.0},{"TIMESTAMP":1710705600000,"AirTF":56.49457,"RH":27.6847,"Rainfall_Tot":0.0},{"TIMESTAMP":1710706500000,"AirTF":0.0,"RH":0.0,"Rainfall_Tot":0.0},{"TIMESTAMP":1710707400000,"AirTF":0.0,"RH":0.0,"Rainfall_Tot":0.0},{"TIMESTAMP":1710708300000,"AirTF":0.0,"RH":0.0,"Rainfall_Tot":0.0},{"TIMESTAMP":1710709200000,"AirTF":0.0,"RH":0.0,"Rainfall_Tot":0.0},{"TIMESTAMP":1710710100000,"AirTF":0.0,"RH":0.0,"Rainfall_Tot":0.0},{"TIMESTAMP":1710711000000,"AirTF":0.0,"RH":0.0,"Rainfall_Tot":0.0},{"TIMESTAMP":1710711900000,"AirTF":0.0,"RH":0.0,"Rainfall_Tot":0.0},{"TIMESTAMP":1710712800000,"AirTF":0.0,"RH":0.0,"Rainfall_Tot":0.0},{"TIMESTAMP":1710713700000,"AirTF":0.0,"RH":0.0,"Rainfall_Tot":0.0},{"TIMESTAMP":1710714600000,"AirTF":0.0,"RH":0.0,"Rainfall_Tot":0.0},{"TIMESTAMP":1710715500000,"AirTF":0.0,"RH":0.0,"Rainfall_Tot":0.0},{"TIMESTAMP":1710716400000,"AirTF":0.0,"RH":0.0,"Rainfall_Tot":0.0},{"TIMESTAMP":1710717300000,"AirTF":0.0,"RH":0.0,"Rainfall_Tot":0.0},{"TIMESTAMP":1710718200000,"AirTF":0.0,"RH":0.0,"Rainfall_Tot":0.0},{"TIMESTAMP":1710719100000,"AirTF":0.0,"RH":0.0,"Rainfall_Tot":0.0},{"TIMESTAMP":1710720000000,"AirTF":0.0,"RH":0.0,"Rainfall_Tot":0.0},{"TIMESTAMP":1710720900000,"AirTF":0.0,"RH":0.0,"Rainfall_Tot":0.0},{"TIMESTAMP":1710721800000,"AirTF":0.0,"RH":0.0,"Rainfall_Tot":0.0},{"TIMESTAMP":1710722700000,"AirTF":0.0,"RH":0.0,"Rainfall_Tot":0.0},{"TIMESTAMP":1710723600000,"AirTF":0.0,"RH":0.0,"Rainfall_Tot":0.0},{"TIMESTAMP":1710724500000,"AirTF":0.0,"RH":0.0,"Rainfall_Tot":0.0},{"TIMESTAMP":1710725400000,"AirTF":0.0,"RH":0.0,"Rainfall_Tot":0.0},{"TIMESTAMP":1710726300000,"AirTF":0.0,"RH":0.0,"Rainfall_Tot":0.0},{"TIMESTAMP":1710727200000,"AirTF":0.0,"RH":0.0,"Rainfall_Tot":0.0},{"TIMESTAMP":1710728100000,"AirTF":0.0,"RH":0.0,"Rainfall_Tot":0.0},{"TIMESTAMP":1710729000000,"AirTF":0.0,"RH":0.0,"Rainfall_Tot":0.0},{"TIMESTAMP":1710729900000,"AirTF":0.0,"RH":0.0,"Rainfall_Tot":0.0},{"TIMESTAMP":1710730800000,"AirTF":0.0,"RH":0.0,"Rainfall_Tot":0.0},{"TIMESTAMP":1710731700000,"AirTF":0.0,"RH":0.0,"Rainfall_Tot":0.0},{"TIMESTAMP":1710732600000,"AirTF":0.0,"RH":0.0,"Rainfall_Tot":0.0},{"TIMESTAMP":1710733500000,"AirTF":0.0,"RH":0.0,"Rainfall_Tot":0.0},{"TIMESTAMP":1710734400000,"AirTF":0.0,"RH":0.0,"Rainfall_Tot":0.0},{"TIMESTAMP":1710735300000,"AirTF":0.0,"RH":0.0,"Rainfall_Tot":0.0},{"TIMESTAMP":1710736200000,"AirTF":0.0,"RH":0.0,"Rainfall_Tot":0.0},{"TIMESTAMP":1710737100000,"AirTF":0.0,"RH":0.0,"Rainfall_Tot":0.0},{"TIMESTAMP":1710738000000,"AirTF":0.0,"RH":0.0,"Rainfall_Tot":0.0},{"TIMESTAMP":1710738900000,"AirTF":0.0,"RH":0.0,"Rainfall_Tot":0.0},{"TIMESTAMP":1710739800000,"AirTF":0.0,"RH":0.0,"Rainfall_Tot":0.0},{"TIMESTAMP":1710740700000,"AirTF":0.0,"RH":0.0,"Rainfall_Tot":0.0},{"TIMESTAMP":1710741600000,"AirTF":0.0,"RH":0.0,"Rainfall_Tot":0.0},{"TIMESTAMP":1710742500000,"AirTF":0.0,"RH":0.0,"Rainfall_Tot":0.0},{"TIMESTAMP":1710743400000,"AirTF":0.0,"RH":0.0,"Rainfall_Tot":0.0},{"TIMESTAMP":1710744300000,"AirTF":0.0,"RH":0.0,"Rainfall_Tot":0.0},{"TIMESTAMP":1710745200000,"AirTF":0.0,"RH":0.0,"Rainfall_Tot":0.0},{"TIMESTAMP":1710746100000,"AirTF":0.0,"RH":0.0,"Rainfall_Tot":0.0},{"TIMESTAMP":1710747000000,"AirTF":0.0,"RH":0.0,"Rainfall_Tot":0.0},{"TIMESTAMP":1710747900000,"AirTF":0.0,"RH":0.0,"Rainfall_Tot":0.0},{"TIMESTAMP":1710748800000,"AirTF":0.0,"RH":0.0,"Rainfall_Tot":0.0},{"TIMESTAMP":1710749700000,"AirTF":0.0,"RH":0.0,"Rainfall_Tot":0.0},{"TIMESTAMP":1710750600000,"AirTF":0.0,"RH":0.0,"Rainfall_Tot":0.0},{"TIMESTAMP":1710751500000,"AirTF":0.0,"RH":0.0,"Rainfall_Tot":0.0},{"TIMESTAMP":1710752400000,"AirTF":46.14017,"RH":44.27353,"Rainfall_Tot":0.0},{"TIMESTAMP":1710753300000,"AirTF":45.88742,"RH":41.51407,"Rainfall_Tot":0.0},{"TIMESTAMP":1710754200000,"AirTF":47.16214,"RH":43.16242,"Rainfall_Tot":0.0},{"TIMESTAMP":1710755100000,"AirTF":47.27753,"RH":42.22836,"Rainfall_Tot":0.0},{"TIMESTAMP":1710756000000,"AirTF":47.43961,"RH":41.97347,"Rainfall_Tot":0.0},{"TIMESTAMP":1710756900000,"AirTF":47.68962,"RH":41.0974,"Rainfall_Tot":0.0},{"TIMESTAMP":1710757800000,"AirTF":48.68137,"RH":39.14532,"Rainfall_Tot":0.0},{"TIMESTAMP":1710758700000,"AirTF":49.91215,"RH":36.79795,"Rainfall_Tot":0.0},{"TIMESTAMP":1710759600000,"AirTF":48.68413,"RH":35.86388,"Rainfall_Tot":0.0},{"TIMESTAMP":1710760500000,"AirTF":49.72808,"RH":35.10534,"Rainfall_Tot":0.0},{"TIMESTAMP":1710761400000,"AirTF":47.21159,"RH":33.44783,"Rainfall_Tot":0.0},{"TIMESTAMP":1710762300000,"AirTF":51.87643,"RH":37.37487,"Rainfall_Tot":0.0},{"TIMESTAMP":1710763200000,"AirTF":53.59346,"RH":37.83427,"Rainfall_Tot":0.0},{"TIMESTAMP":1710764100000,"AirTF":53.44511,"RH":38.40356,"Rainfall_Tot":0.0},{"TIMESTAMP":1710765000000,"AirTF":56.56599,"RH":36.45454,"Rainfall_Tot":0.0},{"TIMESTAMP":1710765900000,"AirTF":52.97258,"RH":35.94783,"Rainfall_Tot":0.0},{"TIMESTAMP":1710766800000,"AirTF":49.85995,"RH":34.56809,"Rainfall_Tot":0.0},{"TIMESTAMP":1710767700000,"AirTF":53.29677,"RH":33.31809,"Rainfall_Tot":0.0},{"TIMESTAMP":1710768600000,"AirTF":52.31874,"RH":35.40601,"Rainfall_Tot":0.0},{"TIMESTAMP":1710769500000,"AirTF":56.07973,"RH":33.0281,"Rainfall_Tot":0.0},{"TIMESTAMP":1710770400000,"AirTF":57.02753,"RH":32.85869,"Rainfall_Tot":0.0},{"TIMESTAMP":1710771300000,"AirTF":50.98357,"RH":33.35778,"Rainfall_Tot":0.0},{"TIMESTAMP":1710772200000,"AirTF":53.00006,"RH":30.03818,"Rainfall_Tot":0.0},{"TIMESTAMP":1710773100000,"AirTF":55.68138,"RH":31.73995,"Rainfall_Tot":0.0},{"TIMESTAMP":1710774000000,"AirTF":50.96709,"RH":30.99971,"Rainfall_Tot":0.0},{"TIMESTAMP":1710774900000,"AirTF":53.56324,"RH":30.86235,"Rainfall_Tot":0.0},{"TIMESTAMP":1710775800000,"AirTF":52.21984,"RH":32.28329,"Rainfall_Tot":0.0},{"TIMESTAMP":1710776700000,"AirTF":52.0083,"RH":35.69447,"Rainfall_Tot":0.0},{"TIMESTAMP":1710777600000,"AirTF":51.75006,"RH":31.03329,"Rainfall_Tot":0.0},{"TIMESTAMP":1710778500000,"AirTF":55.0605,"RH":33.83854,"Rainfall_Tot":0.0},{"TIMESTAMP":1710779400000,"AirTF":54.73907,"RH":30.67615,"Rainfall_Tot":0.0},{"TIMESTAMP":1710780300000,"AirTF":52.73907,"RH":31.26986,"Rainfall_Tot":0.0},{"TIMESTAMP":1710781200000,"AirTF":53.84621,"RH":31.06229,"Rainfall_Tot":0.0}]